[
  {
    "pair": "BTC-USD",
    "price": 115753.87,
    "rsi": 55.7701814340937,
    "ema_50": 115513.33065490378,
    "ema_uptrend": true,
    "macd_line": 90.87947609389084,
    "signal_line": 81.79152848450177,
    "macd_bullish": true,
    "atr": 376.95142857143117,
    "volatility_ratio": 0.0032564909369460493,
    "can_buy": false,
    "buy_reason": "RSI not oversold: 55.77",
    "throttle_status": "\u2705 Ready",
    "timestamp": "2025-08-01T16:15:47.576934+00:00"
  },
  {
    "pair": "ETH-USD",
    "price": 3695.61,
    "rsi": 54.8710296312086,
    "ema_50": 3686.177031785022,
    "ema_uptrend": true,
    "macd_line": 2.096210888265432,
    "signal_line": 1.886589799438889,
    "macd_bullish": true,
    "atr": 21.497142857142826,
    "volatility_ratio": 0.005816940331134191,
    "can_buy": false,
    "buy_reason": "RSI not oversold: 54.87",
    "throttle_status": "\u2705 Ready",
    "timestamp": "2025-08-01T16:15:47.685495+00:00"
  },
  {
    "pair": "XRP-USD",
    "price": 3.0253,
    "rsi": 60.22364217252401,
    "ema_50": 2.9954324588741033,
    "ema_uptrend": true,
    "macd_line": 0.010103461054006502,
    "signal_line": 0.009093114948605851,
    "macd_bullish": true,
    "atr": 0.023707142857142927,
    "volatility_ratio": 0.007836294865680405,
    "can_buy": false,
    "buy_reason": "RSI not oversold: 60.22",
    "throttle_status": "\u2705 Ready",
    "timestamp": "2025-08-01T16:15:47.781996+00:00"
  },
  {
    "pair": "ADA-USD",
    "price": 0.7397,
    "rsi": 58.35140997830803,
    "ema_50": 0.733246177295722,
    "ema_uptrend": true,
    "macd_line": 0.002269091297395387,
    "signal_line": 0.0020421821676558484,
    "macd_bullish": true,
    "atr": 0.005671428571428565,
    "volatility_ratio": 0.007667200988817852,
    "can_buy": false,
    "buy_reason": "RSI not oversold: 58.35",
    "throttle_status": "\u2705 Ready",
    "timestamp": "2025-08-01T16:15:47.902611+00:00"
  },
  {
    "pair": "SOL-USD",
    "price": 172.08,
    "rsi": 64.24870466321221,
    "ema_50": 170.68043744218673,
    "ema_uptrend": true,
    "macd_line": 0.5437496286986914,
    "signal_line": 0.4893746658288222,
    "macd_bullish": true,
    "atr": 1.0921428571428626,
    "volatility_ratio": 0.006346715813243042,
    "can_buy": false,
    "buy_reason": "RSI not oversold: 64.25",
    "throttle_status": "\u2705 Ready",
    "timestamp": "2025-08-01T16:15:48.014143+00:00"
  },
  {
    "pair": "DOGE-USD",
    "price": 0.20976,
    "rsi": 58.09859154929578,
    "ema_50": 0.20815856796088797,
    "ema_uptrend": true,
    "macd_line": 0.0005802011414014763,
    "signal_line": 0.0005221810272613286,
    "macd_bullish": true,
    "atr": 0.0018257142857142836,
    "volatility_ratio": 0.008703824779339644,
    "can_buy": false,
    "buy_reason": "RSI not oversold: 58.10",
    "throttle_status": "\u2705 Ready",
    "timestamp": "2025-08-01T16:15:48.131249+00:00"
  },
  {
    "pair": "DOT-USD",
    "price": 3.68,
    "rsi": 53.46938775510202,
    "ema_50": 3.6703328450348582,
    "ema_uptrend": true,
    "macd_line": 0.003823134213384094,
    "signal_line": 0.0034408207920456845,
    "macd_bullish": true,
    "atr": 0.02807142857142862,
    "volatility_ratio": 0.007628105590062125,
    "can_buy": false,
    "buy_reason": "RSI not oversold: 53.47",
    "throttle_status": "\u2705 Ready",
    "timestamp": "2025-08-01T16:15:48.241236+00:00"
  },
  {
    "pair": "AVAX-USD",
    "price": 22.5,
    "rsi": 57.9310344827586,
    "ema_50": 22.29414196243014,
    "ema_uptrend": true,
    "macd_line": 0.058483126624302884,
    "signal_line": 0.0526348139618726,
    "macd_bullish": true,
    "atr": 0.16999999999999993,
    "volatility_ratio": 0.007555555555555552,
    "can_buy": false,
    "buy_reason": "RSI not oversold: 57.93",
    "throttle_status": "\u2705 Ready",
    "timestamp": "2025-08-01T16:15:48.347332+00:00"
  },
  {
    "pair": "MATIC-USD",
    "price": 0.2046,
    "rsi": 57.812499999999964,
    "ema_50": 0.2030894302580236,
    "ema_uptrend": true,
    "macd_line": 0.0005987131993538952,
    "signal_line": 0.0005388418794185058,
    "macd_bullish": true,
    "atr": 0.0014785714285714263,
    "volatility_ratio": 0.0072266443234185055,
    "can_buy": false,
    "buy_reason": "RSI not oversold: 57.81",
    "throttle_status": "\u2705 Ready",
    "timestamp": "2025-08-01T16:15:48.452881+00:00"
  },
  {
    "pair": "LINK-USD",
    "price": 16.934,
    "rsi": 57.39371534195937,
    "ema_50": 16.819478568070004,
    "ema_uptrend": true,
    "macd_line": 0.03770897827994091,
    "signal_line": 0.033938080451946816,
    "macd_bullish": true,
    "atr": 0.13192857142857126,
    "volatility_ratio": 0.007790750645362658,
    "can_buy": false,
    "buy_reason": "RSI not oversold: 57.39",
    "throttle_status": "\u2705 Ready",
    "timestamp": "2025-08-01T16:15:48.549842+00:00"
  },
  {
    "pair": "UNI-USD",
    "price": 9.349,
    "rsi": 49.28229665071782,
    "ema_50": 9.328107573218405,
    "ema_uptrend": true,
    "macd_line": 0.005240706317154675,
    "signal_line": 0.004716635685439208,
    "macd_bullish": true,
    "atr": 0.07478571428571446,
    "volatility_ratio": 0.007999327659184347,
    "can_buy": false,
    "buy_reason": "RSI not oversold: 49.28",
    "throttle_status": "\u2705 Ready",
    "timestamp": "2025-08-01T16:15:48.684759+00:00"
  },
  {
    "pair": "LTC-USD",
    "price": 106.1,
    "rsi": 52.25933202357568,
    "ema_50": 105.93861771838007,
    "ema_uptrend": true,
    "macd_line": 0.05347844330962914,
    "signal_line": 0.04813059897866623,
    "macd_bullish": true,
    "atr": 0.6714285714285698,
    "volatility_ratio": 0.006328261747677378,
    "can_buy": false,
    "buy_reason": "RSI not oversold: 52.26",
    "throttle_status": "\u2705 Ready",
    "timestamp": "2025-08-01T16:15:48.789980+00:00"
  },
  {
    "pair": "ATOM-USD",
    "price": 4.207,
    "rsi": 58.84955752212398,
    "ema_50": 4.19125405309355,
    "ema_uptrend": true,
    "macd_line": 0.006905063993326799,
    "signal_line": 0.006214557593994119,
    "macd_bullish": true,
    "atr": 0.028642857142857064,
    "volatility_ratio": 0.006808380590172822,
    "can_buy": false,
    "buy_reason": "RSI not oversold: 58.85",
    "throttle_status": "\u2705 Ready",
    "timestamp": "2025-08-01T16:15:48.885197+00:00"
  },
  {
    "pair": "XLM-USD",
    "price": 0.403583,
    "rsi": 65.03177884983526,
    "ema_50": 0.39650033380963784,
    "ema_uptrend": true,
    "macd_line": 0.0020118869667195005,
    "signal_line": 0.0018106982700475504,
    "macd_bullish": true,
    "atr": 0.003562285714285716,
    "volatility_ratio": 0.008826649572171563,
    "can_buy": false,
    "buy_reason": "RSI not oversold: 65.03",
    "throttle_status": "\u2705 Ready",
    "timestamp": "2025-08-01T16:15:48.991374+00:00"
  },
  {
    "pair": "ALGO-USD",
    "price": 0.2445,
    "rsi": 58.64661654135345,
    "ema_50": 0.24303824446446257,
    "ema_uptrend": true,
    "macd_line": 0.00044068996948282146,
    "signal_line": 0.0003966209725345393,
    "macd_bullish": true,
    "atr": 0.0018285714285714333,
    "volatility_ratio": 0.007478819748758418,
    "can_buy": false,
    "buy_reason": "RSI not oversold: 58.65",
    "throttle_status": "\u2705 Ready",
    "timestamp": "2025-08-01T16:15:49.096156+00:00"
  },
  {
    "pair": "VET-USD",
    "price": 0.02315,
    "rsi": 57.3333333333334,
    "ema_50": 0.022986758017538914,
    "ema_uptrend": true,
    "macd_line": 5.3376535266810854e-05,
    "signal_line": 4.803888174012977e-05,
    "macd_bullish": true,
    "atr": 0.00017642857142857193,
    "volatility_ratio": 0.0076211045973465195,
    "can_buy": false,
    "buy_reason": "RSI not oversold: 57.33",
    "throttle_status": "\u2705 Ready",
    "timestamp": "2025-08-01T16:15:49.181180+00:00"
  },
  {
    "pair": "ICP-USD",
    "price": 5.231,
    "rsi": 52.31316725978662,
    "ema_50": 5.218080672529086,
    "ema_uptrend": true,
    "macd_line": 0.00407955158669715,
    "signal_line": 0.003671596428027435,
    "macd_bullish": true,
    "atr": 0.03564285714285712,
    "volatility_ratio": 0.006813775022530515,
    "can_buy": false,
    "buy_reason": "RSI not oversold: 52.31",
    "throttle_status": "\u2705 Ready",
    "timestamp": "2025-08-01T16:15:49.282031+00:00"
  },
  {
    "pair": "FIL-USD",
    "price": 2.392,
    "rsi": 57.232704402515665,
    "ema_50": 2.3753839133308854,
    "ema_uptrend": true,
    "macd_line": 0.006490554425106598,
    "signal_line": 0.005841498982595938,
    "macd_bullish": true,
    "atr": 0.018857142857142777,
    "volatility_ratio": 0.007883420926899155,
    "can_buy": false,
    "buy_reason": "RSI not oversold: 57.23",
    "throttle_status": "\u2705 Ready",
    "timestamp": "2025-08-01T16:15:49.376106+00:00"
  },
  {
    "pair": "ETC-USD",
    "price": 20.64,
    "rsi": 61.01694915254229,
    "ema_50": 20.437758597901787,
    "ema_uptrend": true,
    "macd_line": 0.05807048435024598,
    "signal_line": 0.05226343591522138,
    "macd_bullish": true,
    "atr": 0.13928571428571448,
    "volatility_ratio": 0.006748338870431903,
    "can_buy": false,
    "buy_reason": "RSI not oversold: 61.02",
    "throttle_status": "\u2705 Ready",
    "timestamp": "2025-08-01T16:15:49.476459+00:00"
  },
  {
    "pair": "OP-USD",
    "price": 0.667,
    "rsi": 53.33333333333333,
    "ema_50": 0.6631633751697408,
    "ema_uptrend": true,
    "macd_line": 0.0014529282939036436,
    "signal_line": 0.0013076354645132793,
    "macd_bullish": true,
    "atr": 0.006357142857142862,
    "volatility_ratio": 0.00953094881130864,
    "can_buy": false,
    "buy_reason": "RSI not oversold: 53.33",
    "throttle_status": "\u2705 Ready",
    "timestamp": "2025-08-01T16:15:49.590462+00:00"
  },
  {
    "pair": "ARB-USD",
    "price": 0.3978,
    "rsi": 56.6225165562914,
    "ema_50": 0.394137618583634,
    "ema_uptrend": true,
    "macd_line": 0.0012221720504008715,
    "signal_line": 0.0010999548453607844,
    "macd_bullish": true,
    "atr": 0.003764285714285716,
    "volatility_ratio": 0.009462759462759467,
    "can_buy": false,
    "buy_reason": "RSI not oversold: 56.62",
    "throttle_status": "\u2705 Ready",
    "timestamp": "2025-08-01T16:15:49.691122+00:00"
  }
]