[
  {
    "pair": "BTC-USD",
    "price": 116610.91,
    "rsi": 64.0561517754505,
    "ema_50": 116159.22878104981,
    "ema_uptrend": true,
    "macd_line": 170.46367083447694,
    "signal_line": 153.41730375102927,
    "macd_bullish": true,
    "atr": 222.75357142857476,
    "volatility_ratio": 0.001910229252379342,
    "can_buy": false,
    "buy_reason": "RSI not oversold: 64.06",
    "throttle_status": "\u2705 Ready",
    "timestamp": "2025-08-01T13:35:03.648873+00:00"
  },
  {
    "pair": "ETH-USD",
    "price": 3744.03,
    "rsi": 67.40729390131771,
    "ema_50": 3716.494570185416,
    "ema_uptrend": true,
    "macd_line": 9.845697331528754,
    "signal_line": 8.861127598375878,
    "macd_bullish": true,
    "atr": 13.659285714285716,
    "volatility_ratio": 0.003648284259016545,
    "can_buy": false,
    "buy_reason": "RSI not oversold: 67.41",
    "throttle_status": "\u2705 Ready",
    "timestamp": "2025-08-01T13:35:03.754842+00:00"
  },
  {
    "pair": "XRP-USD",
    "price": 3.0525,
    "rsi": 61.105424769702864,
    "ema_50": 3.0288912549540505,
    "ema_uptrend": true,
    "macd_line": 0.008483759662830881,
    "signal_line": 0.007635383696547793,
    "macd_bullish": true,
    "atr": 0.015392857142857144,
    "volatility_ratio": 0.005042705042705042,
    "can_buy": false,
    "buy_reason": "RSI not oversold: 61.11",
    "throttle_status": "\u2705 Ready",
    "timestamp": "2025-08-01T13:35:03.848291+00:00"
  },
  {
    "pair": "ADA-USD",
    "price": 0.7503,
    "rsi": 59.1549295774648,
    "ema_50": 0.7431550272897667,
    "ema_uptrend": true,
    "macd_line": 0.0026060267385333846,
    "signal_line": 0.002345424064680046,
    "macd_bullish": true,
    "atr": 0.004085714285714296,
    "volatility_ratio": 0.005445440871270553,
    "can_buy": false,
    "buy_reason": "RSI not oversold: 59.15",
    "throttle_status": "\u2705 Ready",
    "timestamp": "2025-08-01T13:35:03.933493+00:00"
  },
  {
    "pair": "SOL-USD",
    "price": 175.42,
    "rsi": 63.888888888889014,
    "ema_50": 172.95441390987273,
    "ema_uptrend": true,
    "macd_line": 0.6577856542411951,
    "signal_line": 0.5920070888170755,
    "macd_bullish": true,
    "atr": 0.8878571428571433,
    "volatility_ratio": 0.005061322214440448,
    "can_buy": false,
    "buy_reason": "RSI not oversold: 63.89",
    "throttle_status": "\u2705 Ready",
    "timestamp": "2025-08-01T13:35:04.022740+00:00"
  },
  {
    "pair": "DOGE-USD",
    "price": 0.21372,
    "rsi": 63.01369863013702,
    "ema_50": 0.21109634926587514,
    "ema_uptrend": true,
    "macd_line": 0.0008839815663528872,
    "signal_line": 0.0007955834097175985,
    "macd_bullish": true,
    "atr": 0.001252857142857147,
    "volatility_ratio": 0.005862142723456611,
    "can_buy": false,
    "buy_reason": "RSI not oversold: 63.01",
    "throttle_status": "\u2705 Ready",
    "timestamp": "2025-08-01T13:35:04.106352+00:00"
  },
  {
    "pair": "DOT-USD",
    "price": 3.742,
    "rsi": 61.70212765957453,
    "ema_50": 3.7055529918826875,
    "ema_uptrend": true,
    "macd_line": 0.014272137812395336,
    "signal_line": 0.012844924031155803,
    "macd_bullish": true,
    "atr": 0.02185714285714286,
    "volatility_ratio": 0.005841032297472705,
    "can_buy": false,
    "buy_reason": "RSI not oversold: 61.70",
    "throttle_status": "\u2705 Ready",
    "timestamp": "2025-08-01T13:35:04.191858+00:00"
  },
  {
    "pair": "AVAX-USD",
    "price": 22.85,
    "rsi": 62.82051282051282,
    "ema_50": 22.58497525967764,
    "ema_uptrend": true,
    "macd_line": 0.09550168837866835,
    "signal_line": 0.08595151954080152,
    "macd_bullish": true,
    "atr": 0.11857142857142884,
    "volatility_ratio": 0.0051891216005001675,
    "can_buy": false,
    "buy_reason": "RSI not oversold: 62.82",
    "throttle_status": "\u2705 Ready",
    "timestamp": "2025-08-01T13:35:04.286592+00:00"
  },
  {
    "pair": "MATIC-USD",
    "price": 0.2072,
    "rsi": 49.15254237288145,
    "ema_50": 0.20573634375260957,
    "ema_uptrend": true,
    "macd_line": 0.0004268337083628837,
    "signal_line": 0.00038415033752659536,
    "macd_bullish": true,
    "atr": 0.0009857142857142881,
    "volatility_ratio": 0.004757308328736912,
    "can_buy": false,
    "buy_reason": "RSI not oversold: 49.15",
    "throttle_status": "\u2705 Ready",
    "timestamp": "2025-08-01T13:35:04.371717+00:00"
  },
  {
    "pair": "LINK-USD",
    "price": 17.196,
    "rsi": 61.74698795180724,
    "ema_50": 17.005135791141736,
    "ema_uptrend": true,
    "macd_line": 0.061513083632810606,
    "signal_line": 0.055361775269529546,
    "macd_bullish": true,
    "atr": 0.09971428571428577,
    "volatility_ratio": 0.005798690725417874,
    "can_buy": false,
    "buy_reason": "RSI not oversold: 61.75",
    "throttle_status": "\u2705 Ready",
    "timestamp": "2025-08-01T13:35:04.460407+00:00"
  },
  {
    "pair": "UNI-USD",
    "price": 9.506,
    "rsi": 61.49584487534632,
    "ema_50": 9.416334650488107,
    "ema_uptrend": true,
    "macd_line": 0.03292656643029446,
    "signal_line": 0.029633909787265014,
    "macd_bullish": true,
    "atr": 0.0507857142857138,
    "volatility_ratio": 0.005342490457154829,
    "can_buy": false,
    "buy_reason": "RSI not oversold: 61.50",
    "throttle_status": "\u2705 Ready",
    "timestamp": "2025-08-01T13:35:04.543092+00:00"
  },
  {
    "pair": "LTC-USD",
    "price": 108.35,
    "rsi": 61.36363636363642,
    "ema_50": 107.2335977002435,
    "ema_uptrend": true,
    "macd_line": 0.4065001385781244,
    "signal_line": 0.365850124720312,
    "macd_bullish": true,
    "atr": 0.4507142857142859,
    "volatility_ratio": 0.0041597995912716745,
    "can_buy": false,
    "buy_reason": "RSI not oversold: 61.36",
    "throttle_status": "\u2705 Ready",
    "timestamp": "2025-08-01T13:35:04.633089+00:00"
  },
  {
    "pair": "ATOM-USD",
    "price": 4.298,
    "rsi": 66.43356643356657,
    "ema_50": 4.238972145648967,
    "ema_uptrend": true,
    "macd_line": 0.018874359559241327,
    "signal_line": 0.016986923603317196,
    "macd_bullish": true,
    "atr": 0.025071428571428633,
    "volatility_ratio": 0.005833277936581813,
    "can_buy": false,
    "buy_reason": "RSI not oversold: 66.43",
    "throttle_status": "\u2705 Ready",
    "timestamp": "2025-08-01T13:35:04.740384+00:00"
  },
  {
    "pair": "XLM-USD",
    "price": 0.406688,
    "rsi": 54.75848563968672,
    "ema_50": 0.4028116108548526,
    "ema_uptrend": true,
    "macd_line": 0.0011366042266168774,
    "signal_line": 0.0010229438039551896,
    "macd_bullish": true,
    "atr": 0.0025025714285714295,
    "volatility_ratio": 0.0061535413598911935,
    "can_buy": false,
    "buy_reason": "RSI not oversold: 54.76",
    "throttle_status": "\u2705 Ready",
    "timestamp": "2025-08-01T13:35:04.821954+00:00"
  },
  {
    "pair": "ALGO-USD",
    "price": 0.251,
    "rsi": 64.34782608695639,
    "ema_50": 0.24717169568115419,
    "ema_uptrend": true,
    "macd_line": 0.0014693614781616238,
    "signal_line": 0.0013224253303454614,
    "macd_bullish": true,
    "atr": 0.0016214285714285773,
    "volatility_ratio": 0.006459874786568037,
    "can_buy": false,
    "buy_reason": "RSI not oversold: 64.35",
    "throttle_status": "\u2705 Ready",
    "timestamp": "2025-08-01T13:35:04.910741+00:00"
  },
  {
    "pair": "VET-USD",
    "price": 0.02345,
    "rsi": 58.24175824175831,
    "ema_50": 0.023228328037056517,
    "ema_uptrend": true,
    "macd_line": 7.069196133328501e-05,
    "signal_line": 6.362276519995651e-05,
    "macd_bullish": true,
    "atr": 0.00012642857142857123,
    "volatility_ratio": 0.00539141029546146,
    "can_buy": false,
    "buy_reason": "RSI not oversold: 58.24",
    "throttle_status": "\u2705 Ready",
    "timestamp": "2025-08-01T13:35:04.999239+00:00"
  },
  {
    "pair": "ICP-USD",
    "price": 5.325,
    "rsi": 58.411214953271156,
    "ema_50": 5.281324835066766,
    "ema_uptrend": true,
    "macd_line": 0.018790335677551617,
    "signal_line": 0.016911302109796456,
    "macd_bullish": true,
    "atr": 0.029357142857142766,
    "volatility_ratio": 0.005513078470824932,
    "can_buy": false,
    "buy_reason": "RSI not oversold: 58.41",
    "throttle_status": "\u2705 Ready",
    "timestamp": "2025-08-01T13:35:05.094077+00:00"
  },
  {
    "pair": "FIL-USD",
    "price": 2.439,
    "rsi": 58.585858585858745,
    "ema_50": 2.408067483672757,
    "ema_uptrend": true,
    "macd_line": 0.009581643555309327,
    "signal_line": 0.008623479199778395,
    "macd_bullish": true,
    "atr": 0.014500000000000148,
    "volatility_ratio": 0.005945059450594567,
    "can_buy": false,
    "buy_reason": "RSI not oversold: 58.59",
    "throttle_status": "\u2705 Ready",
    "timestamp": "2025-08-01T13:35:05.185666+00:00"
  },
  {
    "pair": "ETC-USD",
    "price": 21.03,
    "rsi": 60.273972602739676,
    "ema_50": 20.776329327711476,
    "ema_uptrend": true,
    "macd_line": 0.09243207175085288,
    "signal_line": 0.0831888645757676,
    "macd_bullish": true,
    "atr": 0.09714285714285735,
    "volatility_ratio": 0.004619251409550991,
    "can_buy": false,
    "buy_reason": "RSI not oversold: 60.27",
    "throttle_status": "\u2705 Ready",
    "timestamp": "2025-08-01T13:35:05.275311+00:00"
  },
  {
    "pair": "OP-USD",
    "price": 0.684,
    "rsi": 66.6666666666668,
    "ema_50": 0.6735389299277156,
    "ema_uptrend": true,
    "macd_line": 0.0038989808722366126,
    "signal_line": 0.0035090827850129515,
    "macd_bullish": true,
    "atr": 0.003928571428571416,
    "volatility_ratio": 0.005743525480367566,
    "can_buy": false,
    "buy_reason": "RSI not oversold: 66.67",
    "throttle_status": "\u2705 Ready",
    "timestamp": "2025-08-01T13:35:05.358244+00:00"
  },
  {
    "pair": "ARB-USD",
    "price": 0.4058,
    "rsi": 59.999999999999844,
    "ema_50": 0.40069629217702063,
    "ema_uptrend": true,
    "macd_line": 0.0017775018161553802,
    "signal_line": 0.0015997516345398423,
    "macd_bullish": true,
    "atr": 0.002592857142857143,
    "volatility_ratio": 0.006389495177075266,
    "can_buy": false,
    "buy_reason": "RSI not oversold: 60.00",
    "throttle_status": "\u2705 Ready",
    "timestamp": "2025-08-01T13:35:05.442025+00:00"
  }
]